MANIFEST.in
README.rst
cinc.cpp
cinc.py
setup.py
cinc.egg-info/PKG-INFO
cinc.egg-info/SOURCES.txt
cinc.egg-info/dependency_links.txt
cinc.egg-info/top_level.txt
testcases/__init__.py
testcases/testcinc.py