Metadata-Version: 1.1
Name: cinc
Version: 2.0.post1
Summary: Fast fixed-sized C-like integer types.
Home-page: https://pypi.org/project/cinc/
Author: Mark Sierak
Author-email: mZarjk_@mailfence.com
License: UNKNOWN
Platform: UNKNOWN
Classifier: Development Status :: 5 - Production/Stable
Classifier: Intended Audience :: Developers
Classifier: License :: OSI Approved :: GNU Lesser General Public License v3 or later (LGPLv3+)
Classifier: Operating System :: OS Independent
Classifier: Programming Language :: Python :: 3
Classifier: Programming Language :: Python :: Implementation :: CPython
Classifier: Topic :: Software Development :: Libraries :: Python Modules
